README.rst
setup.cfg
setup.py
kimo/__init__.py
kimo/_version.py
kimo/cache.py
kimo/cli.py
kimo/defaults.py
kimo/filters.py
kimo/logging.py
kimo/mysql.py
kimo/process.py
kimo/server.py
kimo.egg-info/PKG-INFO
kimo.egg-info/SOURCES.txt
kimo.egg-info/dependency_links.txt
kimo.egg-info/entry_points.txt
kimo.egg-info/requires.txt
kimo.egg-info/top_level.txt