Metadata-Version: 1.2
Name: kimo
Version: 2.0.5
Summary: Finds owner processes of MySQL queries.
Home-page: https://github.com/putdotio/kimo
Author: Omer Murat Yildirim, Cenk Alti
Author-email: omermuratyildirim@gmail.com, cenkalti@gmail.com
License: BSD License
Keywords: kimo mysql query monitor diagnostic
Platform: UNKNOWN
Requires-Python: >=3.5.2
